binance_qsmi/__init__.py
binance_qsmi/app.py
binance_qsmi/commands.py
binance_qsmi/models.py
binance_qsmi-0.0.3.dist-info/METADATA
binance_qsmi-0.0.3.dist-info/WHEEL
binance_qsmi-0.0.3.dist-info/entry_points.txt
binance_qsmi-0.0.3.dist-info/RECORD
